baiduads/__init__.py
baiduads/api_client.py
baiduads/configuration.py
baiduads/exceptions.py
baiduads/model_utils.py
baiduads/rest.py
baiduads/account/__init__.py
baiduads/account/api/__init__.py
baiduads/account/api/account_service.py
baiduads/account/model/__init__.py
baiduads/account/model/api_account_query_request.py
baiduads/account/model/api_account_type.py
baiduads/account/model/api_account_update_request.py
baiduads/account/model/api_offline_time_type.py
baiduads/account/model/get_account_info_request_wrapper.py
baiduads/account/model/get_account_info_response_wrapper.py
baiduads/account/model/get_account_info_response_wrapper_body.py
baiduads/account/model/region_price_factor.py
baiduads/account/model/update_account_info_request_wrapper.py
baiduads/account/model/update_account_info_response_wrapper.py
baiduads/account/model/update_account_info_response_wrapper_body.py
baiduads/accountfeed/__init__.py
baiduads/accountfeed/api/__init__.py
baiduads/accountfeed/api/account_feed_service.py
baiduads/accountfeed/model/__init__.py
baiduads/accountfeed/model/account_feed_type.py
baiduads/accountfeed/model/get_account_feed_request.py
baiduads/accountfeed/model/get_account_feed_request_wrapper.py
baiduads/accountfeed/model/get_account_feed_response_wrapper.py
baiduads/accountfeed/model/get_account_feed_response_wrapper_body.py
baiduads/accountfeed/model/update_account_feed_request_wrapper.py
baiduads/accountfeed/model/update_account_feed_request_wrapper_body.py
baiduads/accountfeed/model/update_account_feed_response_wrapper.py
baiduads/accountfeed/model/update_account_feed_response_wrapper_body.py
baiduads/adgroup/__init__.py
baiduads/adgroup/api/__init__.py
baiduads/adgroup/api/adgroup_service.py
baiduads/adgroup/model/__init__.py
baiduads/adgroup/model/add_adgroup_request_wrapper.py
baiduads/adgroup/model/add_adgroup_response_wrapper.py
baiduads/adgroup/model/add_adgroup_response_wrapper_body.py
baiduads/adgroup/model/api_adgroup_add_request.py
baiduads_sdk_auto-2022.3.0.dist-info/METADATA
baiduads_sdk_auto-2022.3.0.dist-info/WHEEL
baiduads_sdk_auto-2022.3.0.dist-info/top_level.txt
baiduads_sdk_auto-2022.3.0.dist-info/RECORD
